{
  "$schema": "https://json-schema.org/draft/2020-12/schema",
  "schema_version": "1.0.0",
  "generated_from": "docs/events.md",
  "events": [
    { "schema_version": "1.0.0", "contract": "signal_registry", "event_name": "admin_transfer_proposed", "topics_format": ["symbol:event_name"], "body_fields": [{ "name": "current_admin", "type": "Address" }, { "name": "pending_admin", "type": "Address" }, { "name": "expires_at", "type": "u64" }] },
    { "schema_version": "1.0.0", "contract": "signal_registry", "event_name": "admin_transferred", "topics_format": ["symbol:event_name"], "body_fields": [{ "name": "old_admin", "type": "Address" }, { "name": "new_admin", "type": "Address" }] },
    { "schema_version": "1.0.0", "contract": "signal_registry", "event_name": "parameter_updated", "topics_format": ["symbol:event_name"], "body_fields": [{ "name": "parameter", "type": "Symbol" }, { "name": "old_value", "type": "i128" }, { "name": "new_value", "type": "i128" }] },
    { "schema_version": "1.0.0", "contract": "signal_registry", "event_name": "trading_paused", "topics_format": ["symbol:event_name"], "body_fields": [{ "name": "paused_by", "type": "Address" }, { "name": "timestamp", "type": "u64" }, { "name": "expires_at", "type": "u64" }] },
    { "schema_version": "1.0.0", "contract": "signal_registry", "event_name": "trading_unpaused", "topics_format": ["symbol:event_name"], "body_fields": [{ "name": "unpaused_by", "type": "Address" }, { "name": "timestamp", "type": "u64" }] },
    { "schema_version": "1.0.0", "contract": "signal_registry", "event_name": "multisig_signer_added", "topics_format": ["symbol:event_name"], "body_fields": [{ "name": "signer", "type": "Address" }, { "name": "added_by", "type": "Address" }] },
    { "schema_version": "1.0.0", "contract": "signal_registry", "event_name": "multisig_signer_removed", "topics_format": ["symbol:event_name"], "body_fields": [{ "name": "signer", "type": "Address" }, { "name": "removed_by", "type": "Address" }] },
    { "schema_version": "1.0.0", "contract": "signal_registry", "event_name": "fee_collected", "topics_format": ["symbol:event_name", "asset_symbol", "provider", "platform_treasury"], "body_fields": [{ "name": "total_fee", "type": "i128" }, { "name": "platform_fee", "type": "i128" }, { "name": "provider_fee", "type": "i128" }] },
    { "schema_version": "1.0.0", "contract": "signal_registry", "event_name": "signal_expired", "topics_format": ["symbol:event_name"], "body_fields": [{ "name": "signal_id", "type": "u64" }, { "name": "provider", "type": "Address" }, { "name": "expiry_time", "type": "u64" }] },
    { "schema_version": "1.0.0", "contract": "signal_registry", "event_name": "trade_executed", "topics_format": ["symbol:event_name"], "body_fields": [{ "name": "signal_id", "type": "u64" }, { "name": "executor", "type": "Address" }, { "name": "roi", "type": "i128" }, { "name": "volume", "type": "i128" }] },
    { "schema_version": "1.0.0", "contract": "signal_registry", "event_name": "signal_status_changed", "topics_format": ["symbol:event_name"], "body_fields": [{ "name": "signal_id", "type": "u64" }, { "name": "provider", "type": "Address" }, { "name": "old_status", "type": "u32" }, { "name": "new_status", "type": "u32" }] },
    { "schema_version": "1.0.0", "contract": "signal_registry", "event_name": "provider_stats_updated", "topics_format": ["symbol:event_name"], "body_fields": [{ "name": "provider", "type": "Address" }, { "name": "success_rate", "type": "u32" }, { "name": "avg_return", "type": "i128" }, { "name": "total_volume", "type": "i128" }] },
    { "schema_version": "1.0.0", "contract": "signal_registry", "event_name": "follow_gained", "topics_format": ["symbol:event_name"], "body_fields": [{ "name": "user", "type": "Address" }, { "name": "provider", "type": "Address" }, { "name": "new_count", "type": "u32" }] },
    { "schema_version": "1.0.0", "contract": "signal_registry", "event_name": "follow_lost", "topics_format": ["symbol:event_name"], "body_fields": [{ "name": "user", "type": "Address" }, { "name": "provider", "type": "Address" }, { "name": "new_count", "type": "u32" }] },
    { "schema_version": "1.0.0", "contract": "signal_registry", "event_name": "tags_added", "topics_format": ["symbol:event_name"], "body_fields": [{ "name": "signal_id", "type": "u64" }, { "name": "provider", "type": "Address" }, { "name": "tag_count", "type": "u32" }] },
    { "schema_version": "1.0.0", "contract": "signal_registry", "event_name": "collab_signal_created", "topics_format": ["symbol:event_name"], "body_fields": [{ "name": "signal_id", "type": "u64" }, { "name": "authors", "type": "Vec<Address>" }] },
    { "schema_version": "1.0.0", "contract": "signal_registry", "event_name": "collab_signal_approved", "topics_format": ["symbol:event_name"], "body_fields": [{ "name": "signal_id", "type": "u64" }, { "name": "approver", "type": "Address" }] },
    { "schema_version": "1.0.0", "contract": "signal_registry", "event_name": "collab_signal_published", "topics_format": ["symbol:event_name"], "body_fields": [{ "name": "signal_id", "type": "u64" }] },
    { "schema_version": "1.0.0", "contract": "signal_registry", "event_name": "data_exported", "topics_format": ["symbol:event_name"], "body_fields": [{ "name": "requester", "type": "Address" }, { "name": "entity_type", "type": "u32" }, { "name": "record_count", "type": "u32" }] },
    { "schema_version": "1.0.0", "contract": "signal_registry", "event_name": "combo_created", "topics_format": ["symbol:event_name"], "body_fields": [{ "name": "combo_id", "type": "u64" }, { "name": "provider", "type": "Address" }, { "name": "component_count", "type": "u32" }] },
    { "schema_version": "1.0.0", "contract": "signal_registry", "event_name": "combo_executed", "topics_format": ["symbol:event_name"], "body_fields": [{ "name": "combo_id", "type": "u64" }, { "name": "executor", "type": "Address" }, { "name": "combined_roi", "type": "i128" }] },
    { "schema_version": "1.0.0", "contract": "signal_registry", "event_name": "combo_cancelled", "topics_format": ["symbol:event_name"], "body_fields": [{ "name": "combo_id", "type": "u64" }, { "name": "provider", "type": "Address" }] },
    { "schema_version": "1.0.0", "contract": "signal_registry", "event_name": "signal_updated", "topics_format": ["symbol:event_name"], "body_fields": [{ "name": "signal_id", "type": "u64" }, { "name": "version", "type": "u32" }, { "name": "updater", "type": "Address" }] },
    { "schema_version": "1.0.0", "contract": "signal_registry", "event_name": "copy_recorded", "topics_format": ["symbol:event_name"], "body_fields": [{ "name": "user", "type": "Address" }, { "name": "signal_id", "type": "u64" }, { "name": "version", "type": "u32" }] },
    { "schema_version": "1.0.0", "contract": "signal_registry", "event_name": "cross_chain_requested", "topics_format": ["symbol:event_name"], "body_fields": [{ "name": "source_chain", "type": "String" }, { "name": "source_id", "type": "String" }, { "name": "provider", "type": "Address" }] },
    { "schema_version": "1.0.0", "contract": "signal_registry", "event_name": "cross_chain_imported", "topics_format": ["symbol:event_name"], "body_fields": [{ "name": "source_chain", "type": "String" }, { "name": "source_id", "type": "String" }, { "name": "stellar_id", "type": "u64" }] },
    { "schema_version": "1.0.0", "contract": "signal_registry", "event_name": "cross_chain_address_registered", "topics_format": ["symbol:event_name"], "body_fields": [{ "name": "source_chain", "type": "String" }, { "name": "source_address", "type": "String" }, { "name": "stellar_address", "type": "Address" }] },
    { "schema_version": "1.0.0", "contract": "signal_registry", "event_name": "cross_chain_synced", "topics_format": ["symbol:event_name"], "body_fields": [{ "name": "source_chain", "type": "String" }, { "name": "source_id", "type": "String" }, { "name": "new_status", "type": "u32" }] },
    { "schema_version": "1.0.0", "contract": "signal_registry", "event_name": "emergency_paused", "topics_format": ["symbol:event_name"], "body_fields": [{ "name": "category", "type": "String" }, { "name": "paused_by", "type": "Address" }, { "name": "reason", "type": "String" }, { "name": "auto_unpause_at", "type": "Option<u64>" }] },
    { "schema_version": "1.0.0", "contract": "signal_registry", "event_name": "emergency_unpaused", "topics_format": ["symbol:event_name"], "body_fields": [{ "name": "category", "type": "String" }, { "name": "unpaused_by", "type": "Address" }] },
    { "schema_version": "1.0.0", "contract": "signal_registry", "event_name": "circuit_breaker_triggered", "topics_format": ["symbol:event_name"], "body_fields": [{ "name": "category", "type": "String" }, { "name": "reason", "type": "String" }] },
    { "schema_version": "1.0.0", "contract": "signal_registry", "event_name": "guardian_set", "topics_format": ["symbol:event_name"], "body_fields": [{ "name": "guardian", "type": "Address" }] },
    { "schema_version": "1.0.0", "contract": "signal_registry", "event_name": "guardian_revoked", "topics_format": ["symbol:event_name"], "body_fields": [{ "name": "guardian", "type": "Address" }] },

    { "schema_version": "1.0.0", "contract": "oracle", "event_name": "oracle_removed", "topics_format": ["symbol:event_name"], "body_fields": [{ "name": "oracle", "type": "Address" }, { "name": "reason", "type": "String" }] },
    { "schema_version": "1.0.0", "contract": "oracle", "event_name": "weight_adjusted", "topics_format": ["symbol:event_name"], "body_fields": [{ "name": "oracle", "type": "Address" }, { "name": "old_weight", "type": "u32" }, { "name": "new_weight", "type": "u32" }, { "name": "reputation", "type": "u32" }] },
    { "schema_version": "1.0.0", "contract": "oracle", "event_name": "price_submit", "topics_format": ["symbol:event_name"], "body_fields": [{ "name": "oracle", "type": "Address" }, { "name": "price", "type": "i128" }] },
    { "schema_version": "1.0.0", "contract": "oracle", "event_name": "consensus_reached", "topics_format": ["symbol:event_name"], "body_fields": [{ "name": "price", "type": "i128" }, { "name": "num_oracles", "type": "u32" }] },
    { "schema_version": "1.0.0", "contract": "oracle", "event_name": "RECOVER", "topics_format": ["symbol:event_name", "pair"], "body_fields": [{ "name": "timestamp", "type": "u64" }] },
    { "schema_version": "1.0.0", "contract": "oracle", "event_name": "oracle_paused", "topics_format": ["symbol:event_name"], "body_fields": [{ "name": "timestamp", "type": "u64" }] },
    { "schema_version": "1.0.0", "contract": "oracle", "event_name": "gov:proposed", "topics_format": ["symbol:gov", "symbol:proposed"], "body_fields": [{ "name": "id", "type": "u64" }, { "name": "proposer", "type": "Address" }, { "name": "proposal_type", "type": "String" }] },
    { "schema_version": "1.0.0", "contract": "oracle", "event_name": "gov:vote", "topics_format": ["symbol:gov", "symbol:vote"], "body_fields": [{ "name": "proposal_id", "type": "u64" }, { "name": "voter", "type": "Address" }, { "name": "vote", "type": "bool" }, { "name": "weight", "type": "i128" }] },
    { "schema_version": "1.0.0", "contract": "oracle", "event_name": "gov:executed", "topics_format": ["symbol:gov", "symbol:executed"], "body_fields": [{ "name": "id", "type": "u64" }] },
    { "schema_version": "1.0.0", "contract": "oracle", "event_name": "gov:failed", "topics_format": ["symbol:gov", "symbol:failed"], "body_fields": [{ "name": "id", "type": "u64" }, { "name": "reason", "type": "String" }] },
    { "schema_version": "1.0.0", "contract": "oracle", "event_name": "gov:cancelled", "topics_format": ["symbol:gov", "symbol:cancelled"], "body_fields": [{ "name": "id", "type": "u64" }] },
    { "schema_version": "1.0.0", "contract": "oracle", "event_name": "gov:stake", "topics_format": ["symbol:gov", "symbol:stake"], "body_fields": [{ "name": "staker", "type": "Address" }, { "name": "amount", "type": "i128" }, { "name": "total", "type": "i128" }] },
    { "schema_version": "1.0.0", "contract": "oracle", "event_name": "gov:deposit", "topics_format": ["symbol:gov", "symbol:deposit"], "body_fields": [{ "name": "recipient", "type": "Address" }, { "name": "amount", "type": "i128" }, { "name": "returned", "type": "bool" }] },

    { "schema_version": "1.0.0", "contract": "governance", "event_name": "gov:init", "topics_format": ["symbol:gov", "symbol:init"], "body_fields": [{ "name": "admin", "type": "Address" }, { "name": "name", "type": "String" }, { "name": "symbol", "type": "String" }, { "name": "total_supply", "type": "i128" }] },
    { "schema_version": "1.0.0", "contract": "governance", "event_name": "gov:dist", "topics_format": ["symbol:gov", "symbol:dist"], "body_fields": [{ "name": "distribution", "type": "object" }] },
    { "schema_version": "1.0.0", "contract": "governance", "event_name": "gov:vestadd", "topics_format": ["symbol:gov", "symbol:vestadd"], "body_fields": [{ "name": "beneficiary", "type": "Address" }, { "name": "amount", "type": "i128" }, { "name": "cliff_seconds", "type": "i128" }, { "name": "duration_seconds", "type": "i128" }] },
    { "schema_version": "1.0.0", "contract": "governance", "event_name": "gov:vestrel", "topics_format": ["symbol:gov", "symbol:vestrel"], "body_fields": [{ "name": "beneficiary", "type": "Address" }, { "name": "amount", "type": "i128" }] },
    { "schema_version": "1.0.0", "contract": "governance", "event_name": "gov:stake", "topics_format": ["symbol:gov", "symbol:stake"], "body_fields": [{ "name": "holder", "type": "Address" }, { "name": "amount", "type": "i128" }, { "name": "is_stake", "type": "bool" }] },
    { "schema_version": "1.0.0", "contract": "governance", "event_name": "gov:accrue", "topics_format": ["symbol:gov", "symbol:accrue"], "body_fields": [{ "name": "beneficiary", "type": "Address" }, { "name": "volume", "type": "i128" }, { "name": "reward", "type": "i128" }] },
    { "schema_version": "1.0.0", "contract": "governance", "event_name": "gov:claim", "topics_format": ["symbol:gov", "symbol:claim"], "body_fields": [{ "name": "beneficiary", "type": "Address" }, { "name": "amount", "type": "i128" }] },
    { "schema_version": "1.0.0", "contract": "governance", "event_name": "gov:propnew", "topics_format": ["symbol:gov", "symbol:propnew"], "body_fields": [{ "name": "id", "type": "u64" }, { "name": "proposer", "type": "Address" }, { "name": "voting_starts", "type": "u64" }, { "name": "voting_ends", "type": "u64" }] },
    { "schema_version": "1.0.0", "contract": "governance", "event_name": "gov:repvote", "topics_format": ["symbol:gov", "symbol:repvote"], "body_fields": [{ "name": "proposal_id", "type": "u64" }, { "name": "voter", "type": "Address" }, { "name": "token_power", "type": "i128" }, { "name": "weighted", "type": "i128" }, { "name": "multiplier", "type": "u32" }] },
    { "schema_version": "1.0.0", "contract": "governance", "event_name": "gov:badges", "topics_format": ["symbol:gov", "symbol:badges"], "body_fields": [{ "name": "user", "type": "Address" }, { "name": "awarded", "type": "Vec<String>" }] },
    { "schema_version": "1.0.0", "contract": "governance", "event_name": "qv:alloc", "topics_format": ["symbol:qv", "symbol:alloc"], "body_fields": [{ "name": "user", "type": "Address" }, { "name": "capped", "type": "i128" }] },
    { "schema_version": "1.0.0", "contract": "governance", "event_name": "qv:vote", "topics_format": ["symbol:qv", "symbol:vote"], "body_fields": [{ "name": "proposal_id", "type": "u64" }, { "name": "voter", "type": "Address" }, { "name": "votes_desired", "type": "u32" }, { "name": "credits_required", "type": "i128" }] },
    { "schema_version": "1.0.0", "contract": "governance", "event_name": "qv:verified", "topics_format": ["symbol:qv", "symbol:verified"], "body_fields": [{ "name": "user", "type": "Address" }] },
    { "schema_version": "1.0.0", "contract": "governance", "event_name": "qv:bonus", "topics_format": ["symbol:qv", "symbol:bonus"], "body_fields": [{ "name": "user", "type": "Address" }, { "name": "bonus", "type": "i128" }] },
    { "schema_version": "1.0.0", "contract": "governance", "event_name": "qv:refund", "topics_format": ["symbol:qv", "symbol:refund"], "body_fields": [{ "name": "voter", "type": "Address" }, { "name": "proposal_id", "type": "u64" }, { "name": "credits_spent", "type": "i128" }] },
    { "schema_version": "1.0.0", "contract": "governance", "event_name": "gov:cvote", "topics_format": ["symbol:gov", "symbol:cvote"], "body_fields": [{ "name": "pool_id", "type": "u64" }, { "name": "proposal_id", "type": "u64" }, { "name": "voter", "type": "Address" }, { "name": "tokens_to_commit", "type": "i128" }] },
    { "schema_version": "1.0.0", "contract": "governance", "event_name": "upgrade:announced", "topics_format": ["symbol:upgrade", "symbol:announced"], "body_fields": [{ "name": "proposal_id", "type": "u64" }] },

    { "schema_version": "1.0.0", "contract": "governance", "event_name": "gov:votelock", "topics_format": ["symbol:gov", "symbol:votelock"], "body_fields": [{ "name": "actor", "type": "Address" }, { "name": "value", "type": "i128" }] },
    { "schema_version": "1.0.0", "contract": "governance", "event_name": "gov:rewardcfg", "topics_format": ["symbol:gov", "symbol:rewardcfg"], "body_fields": [{ "name": "actor", "type": "Address" }, { "name": "value", "type": "i128" }] },
    { "schema_version": "1.0.0", "contract": "governance", "event_name": "gov:trsasset", "topics_format": ["symbol:gov", "symbol:trsasset"], "body_fields": [{ "name": "actor", "type": "Address" }, { "name": "value", "type": "i128" }] },
    { "schema_version": "1.0.0", "contract": "governance", "event_name": "gov:budget", "topics_format": ["symbol:gov", "symbol:budget"], "body_fields": [{ "name": "actor", "type": "Address" }, { "name": "value", "type": "i128" }] },
    { "schema_version": "1.0.0", "contract": "governance", "event_name": "gov:spend", "topics_format": ["symbol:gov", "symbol:spend"], "body_fields": [{ "name": "actor", "type": "Address" }, { "name": "value", "type": "i128" }] },
    { "schema_version": "1.0.0", "contract": "governance", "event_name": "gov:recur", "topics_format": ["symbol:gov", "symbol:recur"], "body_fields": [{ "name": "actor", "type": "Address" }, { "name": "value", "type": "i128" }] },
    { "schema_version": "1.0.0", "contract": "governance", "event_name": "gov:payrun", "topics_format": ["symbol:gov", "symbol:payrun"], "body_fields": [{ "name": "actor", "type": "Address" }, { "name": "value", "type": "i128" }] },
    { "schema_version": "1.0.0", "contract": "governance", "event_name": "gov:cmtadd", "topics_format": ["symbol:gov", "symbol:cmtadd"], "body_fields": [{ "name": "actor", "type": "Address" }, { "name": "value", "type": "i128" }] },
    { "schema_version": "1.0.0", "contract": "governance", "event_name": "gov:cmtelect", "topics_format": ["symbol:gov", "symbol:cmtelect"], "body_fields": [{ "name": "actor", "type": "Address" }, { "name": "value", "type": "i128" }] },
    { "schema_version": "1.0.0", "contract": "governance", "event_name": "gov:cmtfinal", "topics_format": ["symbol:gov", "symbol:cmtfinal"], "body_fields": [{ "name": "actor", "type": "Address" }, { "name": "value", "type": "i128" }] },
    { "schema_version": "1.0.0", "contract": "governance", "event_name": "gov:cmtrank", "topics_format": ["symbol:gov", "symbol:cmtrank"], "body_fields": [{ "name": "actor", "type": "Address" }, { "name": "value", "type": "i128" }] },
    { "schema_version": "1.0.0", "contract": "governance", "event_name": "gov:cmtover", "topics_format": ["symbol:gov", "symbol:cmtover"], "body_fields": [{ "name": "actor", "type": "Address" }, { "name": "value", "type": "i128" }] },
    { "schema_version": "1.0.0", "contract": "governance", "event_name": "gov:cmtdrop", "topics_format": ["symbol:gov", "symbol:cmtdrop"], "body_fields": [{ "name": "actor", "type": "Address" }, { "name": "value", "type": "i128" }] },
    { "schema_version": "1.0.0", "contract": "governance", "event_name": "gov:target", "topics_format": ["symbol:gov", "symbol:target"], "body_fields": [{ "name": "actor", "type": "Address" }, { "name": "value", "type": "i128" }] },
    { "schema_version": "1.0.0", "contract": "governance", "event_name": "gov:rebalance", "topics_format": ["symbol:gov", "symbol:rebalance"], "body_fields": [{ "name": "actor", "type": "Address" }, { "name": "value", "type": "i128" }] },

    { "schema_version": "1.0.0", "contract": "bridge", "event_name": "wrapped_asset_registered", "topics_format": ["symbol:event_name"], "body_fields": [{ "name": "wrapped_asset", "type": "object" }] },
    { "schema_version": "1.0.0", "contract": "bridge", "event_name": "lock_mint_initiated", "topics_format": ["symbol:event_name", "transfer_id"], "body_fields": [{ "name": "from", "type": "Address" }, { "name": "amount", "type": "i128" }, { "name": "source_chain", "type": "u32" }, { "name": "destination_chain", "type": "u32" }] },
    { "schema_version": "1.0.0", "contract": "bridge", "event_name": "wrapped_asset_minted", "topics_format": ["symbol:event_name", "transfer_id"], "body_fields": [{ "name": "to", "type": "Address" }, { "name": "amount", "type": "i128" }] },
    { "schema_version": "1.0.0", "contract": "bridge", "event_name": "burn_unlock_initiated", "topics_format": ["symbol:event_name", "transfer_id"], "body_fields": [{ "name": "from", "type": "Address" }, { "name": "amount", "type": "i128" }, { "name": "destination_chain", "type": "u32" }] },
    { "schema_version": "1.0.0", "contract": "bridge", "event_name": "burn_unlock_completed", "topics_format": ["symbol:event_name", "transfer_id"], "body_fields": [{ "name": "to", "type": "Address" }, { "name": "amount", "type": "i128" }] },
    { "schema_version": "1.0.0", "contract": "bridge", "event_name": "bridge_transfer_created", "topics_format": ["symbol:event_name", "transfer_id"], "body_fields": [{ "name": "source_chain", "type": "u32" }, { "name": "destination_chain", "type": "u32" }] },
    { "schema_version": "1.0.0", "contract": "bridge", "event_name": "validator_signature_added", "topics_format": ["symbol:event_name", "transfer_id"], "body_fields": [{ "name": "signature_count", "type": "u32" }] },
    { "schema_version": "1.0.0", "contract": "bridge", "event_name": "transfer_approved_minting", "topics_format": ["symbol:event_name", "transfer_id"], "body_fields": [{ "name": "timestamp", "type": "u64" }] },
    { "schema_version": "1.0.0", "contract": "bridge", "event_name": "transfer_complete", "topics_format": ["symbol:event_name", "transfer_id"], "body_fields": [{ "name": "timestamp", "type": "u64" }] },
    { "schema_version": "1.0.0", "contract": "bridge", "event_name": "bridge_fee_collected", "topics_format": ["symbol:event_name", "transfer_id"], "body_fields": [{ "name": "user", "type": "Address" }, { "name": "fee", "type": "i128" }, { "name": "amount", "type": "i128" }, { "name": "net_amount", "type": "i128" }] },
    { "schema_version": "1.0.0", "contract": "bridge", "event_name": "validator_reward_dist", "topics_format": ["symbol:event_name", "bridge_id"], "body_fields": [{ "name": "validator", "type": "Address" }, { "name": "per_validator", "type": "i128" }] },
    { "schema_version": "1.0.0", "contract": "bridge", "event_name": "treasury_allocation", "topics_format": ["symbol:event_name", "bridge_id"], "body_fields": [{ "name": "treasury_share", "type": "i128" }] },
    { "schema_version": "1.0.0", "contract": "bridge", "event_name": "bridge_fees_adjusted", "topics_format": ["symbol:event_name", "bridge_id"], "body_fields": [{ "name": "base_fee_bps", "type": "u32" }, { "name": "utilization", "type": "u32" }] },
    { "schema_version": "1.0.0", "contract": "bridge", "event_name": "bridge_fee_refunded", "topics_format": ["symbol:event_name", "transfer_id"], "body_fields": [{ "name": "user", "type": "Address" }, { "name": "fee_paid", "type": "i128" }, { "name": "reason", "type": "String" }] },

    { "schema_version": "1.0.0", "contract": "auto_trade", "event_name": "trade_executed", "topics_format": ["symbol:event_name", "user", "signal_id"], "body_fields": [{ "name": "trade", "type": "object" }] },
    { "schema_version": "1.0.0", "contract": "auto_trade", "event_name": "risk_limit_block", "topics_format": ["symbol:event_name", "user", "signal_id"], "body_fields": [{ "name": "requested_amount", "type": "i128" }] },
    { "schema_version": "1.0.0", "contract": "auto_trade", "event_name": "risk_config_updated", "topics_format": ["symbol:event_name", "user"], "body_fields": [{ "name": "risk_config", "type": "object" }] },
    { "schema_version": "1.0.0", "contract": "auto_trade", "event_name": "stop_loss_triggered", "topics_format": ["symbol:event_name", "user", "asset_id"], "body_fields": [{ "name": "payload", "type": "object" }] },
    { "schema_version": "1.0.0", "contract": "auto_trade", "event_name": "trailing_stop_triggered", "topics_format": ["symbol:event_name", "user", "asset_id"], "body_fields": [{ "name": "payload", "type": "object" }] },
    { "schema_version": "1.0.0", "contract": "auto_trade", "event_name": "corr_limit_breach", "topics_format": ["symbol:event_name", "user", "new_asset"], "body_fields": [{ "name": "new_amount", "type": "i128" }] },
    { "schema_version": "1.0.0", "contract": "auto_trade", "event_name": "auth_granted", "topics_format": ["symbol:event_name", "user"], "body_fields": [{ "name": "auth_config", "type": "object" }] },
    { "schema_version": "1.0.0", "contract": "auto_trade", "event_name": "auth_revoked", "topics_format": ["symbol:event_name", "user"], "body_fields": [] },
    { "schema_version": "1.0.0", "contract": "auto_trade", "event_name": "user_whitelisted", "topics_format": ["symbol:event_name", "user"], "body_fields": [] },
    { "schema_version": "1.0.0", "contract": "auto_trade", "event_name": "rate_limit_violation", "topics_format": ["symbol:event_name", "user"], "body_fields": [{ "name": "violation_type", "type": "String" }, { "name": "penalty_duration", "type": "u64" }, { "name": "violation_count", "type": "u32" }] },
    { "schema_version": "1.0.0", "contract": "auto_trade", "event_name": "rl_adjust", "topics_format": ["symbol:event_name"], "body_fields": [{ "name": "load_pct", "type": "u32" }, { "name": "per_user_hourly_transfers", "type": "u32" }] },
    { "schema_version": "1.0.0", "contract": "auto_trade", "event_name": "bridge_paused", "topics_format": ["symbol:event_name"], "body_fields": [{ "name": "reason", "type": "String" }] },
    { "schema_version": "1.0.0", "contract": "auto_trade", "event_name": "bridge_unpaused", "topics_format": ["symbol:event_name"], "body_fields": [{ "name": "recovery_id", "type": "u64" }, { "name": "pause_duration", "type": "u64" }] },
    { "schema_version": "1.0.0", "contract": "auto_trade", "event_name": "bridge_auto_unpaused", "topics_format": ["symbol:event_name"], "body_fields": [{ "name": "timestamp", "type": "u64" }] },
    { "schema_version": "1.0.0", "contract": "auto_trade", "event_name": "auto_unpause_scheduled", "topics_format": ["symbol:event_name"], "body_fields": [{ "name": "unpause_at", "type": "u64" }] },
    { "schema_version": "1.0.0", "contract": "auto_trade", "event_name": "recovery_initiated", "topics_format": ["symbol:event_name", "caller"], "body_fields": [{ "name": "recovery_id", "type": "u64" }] },
    { "schema_version": "1.0.0", "contract": "auto_trade", "event_name": "recovery_checklist_complete", "topics_format": ["symbol:event_name"], "body_fields": [{ "name": "recovery_id", "type": "u64" }] },
    { "schema_version": "1.0.0", "contract": "auto_trade", "event_name": "cond_order_created", "topics_format": ["symbol:event_name", "user", "order_id"], "body_fields": [{ "name": "payload", "type": "object" }] },
    { "schema_version": "1.0.0", "contract": "auto_trade", "event_name": "cond_order_cancelled", "topics_format": ["symbol:event_name", "user", "order_id"], "body_fields": [] },
    { "schema_version": "1.0.0", "contract": "auto_trade", "event_name": "cond_order_expired", "topics_format": ["symbol:event_name", "user", "order_id"], "body_fields": [] },
    { "schema_version": "1.0.0", "contract": "auto_trade", "event_name": "cond_order_triggered", "topics_format": ["symbol:event_name", "user", "order_id"], "body_fields": [{ "name": "payload", "type": "object" }] },
    { "schema_version": "1.0.0", "contract": "auto_trade", "event_name": "cond_order_executed", "topics_format": ["symbol:event_name", "user", "order_id"], "body_fields": [{ "name": "payload", "type": "object" }] },
    { "schema_version": "1.0.0", "contract": "auto_trade", "event_name": "TWAPOrderCreated", "topics_format": ["symbol:event_name", "user", "order_id"], "body_fields": [{ "name": "total_amount", "type": "i128" }, { "name": "duration_minutes", "type": "u32" }, { "name": "segments", "type": "u32" }] },
    { "schema_version": "1.0.0", "contract": "auto_trade", "event_name": "TWAPSegmentExecuted", "topics_format": ["symbol:event_name", "order_id", "segment_index"], "body_fields": [{ "name": "fill_amount", "type": "i128" }, { "name": "price", "type": "i128" }] },
    { "schema_version": "1.0.0", "contract": "auto_trade", "event_name": "TWAPSegmentFailed", "topics_format": ["symbol:event_name", "order_id"], "body_fields": [{ "name": "segments_executed", "type": "u32" }] },
    { "schema_version": "1.0.0", "contract": "auto_trade", "event_name": "TWAPOrderComplete", "topics_format": ["symbol:event_name", "order_id"], "body_fields": [{ "name": "filled_amount", "type": "i128" }, { "name": "avg_price", "type": "i128" }] },
    { "schema_version": "1.0.0", "contract": "auto_trade", "event_name": "TWAPAdjusted", "topics_format": ["symbol:event_name", "order_id"], "body_fields": [{ "name": "reason", "type": "String" }, { "name": "new_interval_seconds", "type": "u64" }] },
    { "schema_version": "1.0.0", "contract": "auto_trade", "event_name": "TWAPOrderCancelled", "topics_format": ["symbol:event_name", "order_id"], "body_fields": [{ "name": "filled_amount", "type": "i128" }, { "name": "remaining_amount", "type": "i128" }] },
    { "schema_version": "1.0.0", "contract": "auto_trade", "event_name": "dca_created", "topics_format": ["symbol:event_name"], "body_fields": [{ "name": "payload", "type": "object" }] },
    { "schema_version": "1.0.0", "contract": "auto_trade", "event_name": "dca_purchase", "topics_format": ["symbol:event_name"], "body_fields": [{ "name": "payload", "type": "object" }] },
    { "schema_version": "1.0.0", "contract": "auto_trade", "event_name": "dca_failed", "topics_format": ["symbol:event_name"], "body_fields": [{ "name": "payload", "type": "object" }] },
    { "schema_version": "1.0.0", "contract": "auto_trade", "event_name": "dca_missed", "topics_format": ["symbol:event_name"], "body_fields": [{ "name": "payload", "type": "object" }] },
    { "schema_version": "1.0.0", "contract": "auto_trade", "event_name": "dca_updated", "topics_format": ["symbol:event_name"], "body_fields": [{ "name": "payload", "type": "object" }] },
    { "schema_version": "1.0.0", "contract": "auto_trade", "event_name": "dca_paused_funds", "topics_format": ["symbol:event_name"], "body_fields": [{ "name": "payload", "type": "object" }] },
    { "schema_version": "1.0.0", "contract": "auto_trade", "event_name": "dca_paused", "topics_format": ["symbol:event_name"], "body_fields": [] },
    { "schema_version": "1.0.0", "contract": "auto_trade", "event_name": "dca_resumed", "topics_format": ["symbol:event_name"], "body_fields": [] },
    { "schema_version": "1.0.0", "contract": "auto_trade", "event_name": "mr_strategy_created", "topics_format": ["symbol:event_name"], "body_fields": [{ "name": "payload", "type": "object" }] },
    { "schema_version": "1.0.0", "contract": "auto_trade", "event_name": "mr_trade_opened", "topics_format": ["symbol:event_name"], "body_fields": [{ "name": "payload", "type": "object" }] },
    { "schema_version": "1.0.0", "contract": "auto_trade", "event_name": "mr_position_closed", "topics_format": ["symbol:event_name"], "body_fields": [{ "name": "payload", "type": "object" }] },
    { "schema_version": "1.0.0", "contract": "auto_trade", "event_name": "mr_params_adjusted", "topics_format": ["symbol:event_name"], "body_fields": [{ "name": "payload", "type": "object" }] },
    { "schema_version": "1.0.0", "contract": "auto_trade", "event_name": "grid_init", "topics_format": ["symbol:event_name"], "body_fields": [{ "name": "payload", "type": "object" }] },
    { "schema_version": "1.0.0", "contract": "auto_trade", "event_name": "grid_placed", "topics_format": ["symbol:event_name"], "body_fields": [{ "name": "payload", "type": "object" }] },
    { "schema_version": "1.0.0", "contract": "auto_trade", "event_name": "grid_profit", "topics_format": ["symbol:event_name"], "body_fields": [{ "name": "payload", "type": "object" }] },
    { "schema_version": "1.0.0", "contract": "auto_trade", "event_name": "grid_rebalance", "topics_format": ["symbol:event_name"], "body_fields": [{ "name": "payload", "type": "object" }] },
    { "schema_version": "1.0.0", "contract": "auto_trade", "event_name": "grid_adjusted", "topics_format": ["symbol:event_name"], "body_fields": [{ "name": "payload", "type": "object" }] },
    { "schema_version": "1.0.0", "contract": "auto_trade", "event_name": "pairs_trade_exec", "topics_format": ["symbol:event_name"], "body_fields": [{ "name": "payload", "type": "object" }] },
    { "schema_version": "1.0.0", "contract": "auto_trade", "event_name": "pairs_pos_closed", "topics_format": ["symbol:event_name"], "body_fields": [{ "name": "payload", "type": "object" }] },
    { "schema_version": "1.0.0", "contract": "auto_trade", "event_name": "stat_arb_configured", "topics_format": ["symbol:event_name"], "body_fields": [{ "name": "payload", "type": "object" }] },
    { "schema_version": "1.0.0", "contract": "auto_trade", "event_name": "stat_arb_opened", "topics_format": ["symbol:event_name"], "body_fields": [{ "name": "payload", "type": "object" }] },
    { "schema_version": "1.0.0", "contract": "auto_trade", "event_name": "stat_arb_rebalanced", "topics_format": ["symbol:event_name"], "body_fields": [{ "name": "payload", "type": "object" }] },
    { "schema_version": "1.0.0", "contract": "auto_trade", "event_name": "stat_arb_closed", "topics_format": ["symbol:event_name"], "body_fields": [{ "name": "payload", "type": "object" }] },
    { "schema_version": "1.0.0", "contract": "auto_trade", "event_name": "sentiment_strategy_created", "topics_format": ["symbol:event_name"], "body_fields": [{ "name": "payload", "type": "object" }] },
    { "schema_version": "1.0.0", "contract": "auto_trade", "event_name": "sentiment_trade_executed", "topics_format": ["symbol:event_name"], "body_fields": [{ "name": "payload", "type": "object" }] },
    { "schema_version": "1.0.0", "contract": "auto_trade", "event_name": "sentiment_position_closed", "topics_format": ["symbol:event_name"], "body_fields": [{ "name": "payload", "type": "object" }] },
    { "schema_version": "1.0.0", "contract": "auto_trade", "event_name": "arbitrage_executed", "topics_format": ["symbol:event_name", "user"], "body_fields": [{ "name": "payload", "type": "object" }] },
    { "schema_version": "1.0.0", "contract": "auto_trade", "event_name": "iceberg_created", "topics_format": ["symbol:event_name"], "body_fields": [{ "name": "payload", "type": "object" }] },
    { "schema_version": "1.0.0", "contract": "auto_trade", "event_name": "iceberg_filled", "topics_format": ["symbol:event_name"], "body_fields": [{ "name": "payload", "type": "object" }] },
    { "schema_version": "1.0.0", "contract": "auto_trade", "event_name": "iceberg_replenished", "topics_format": ["symbol:event_name"], "body_fields": [{ "name": "payload", "type": "object" }] },
    { "schema_version": "1.0.0", "contract": "auto_trade", "event_name": "iceberg_complete", "topics_format": ["symbol:event_name"], "body_fields": [{ "name": "payload", "type": "object" }] },
    { "schema_version": "1.0.0", "contract": "auto_trade", "event_name": "iceberg_cancelled", "topics_format": ["symbol:event_name"], "body_fields": [] },
    { "schema_version": "1.0.0", "contract": "auto_trade", "event_name": "referral_registered", "topics_format": ["symbol:event_name"], "body_fields": [{ "name": "payload", "type": "object" }] },
    { "schema_version": "1.0.0", "contract": "auto_trade", "event_name": "referral_reward_earned", "topics_format": ["symbol:event_name"], "body_fields": [{ "name": "payload", "type": "object" }] },
    { "schema_version": "1.0.0", "contract": "auto_trade", "event_name": "hedge_applied", "topics_format": ["symbol:event_name"], "body_fields": [{ "name": "payload", "type": "object" }] },
    { "schema_version": "1.0.0", "contract": "auto_trade", "event_name": "hedges_rebalanced", "topics_format": ["symbol:event_name"], "body_fields": [{ "name": "payload", "type": "object" }] },
    { "schema_version": "1.0.0", "contract": "auto_trade", "event_name": "hedges_removed", "topics_format": ["symbol:event_name"], "body_fields": [{ "name": "payload", "type": "object" }] },
    { "schema_version": "1.0.0", "contract": "auto_trade", "event_name": "risk_parity_rebalance", "topics_format": ["symbol:event_name", "user"], "body_fields": [{ "name": "timestamp", "type": "u64" }] },

    { "schema_version": "1.0.0", "contract": "trade_executor", "event_name": "TradeCancelled", "topics_format": ["symbol:event_name"], "body_fields": [{ "name": "user", "type": "Address" }, { "name": "signal_id", "type": "u64" }] },

    { "schema_version": "1.0.0", "contract": "fee_collector", "event_name": "WithdrawalQueued", "topics_format": ["symbol:event_name"], "body_fields": [{ "name": "recipient", "type": "Address" }, { "name": "token", "type": "Address" }, { "name": "amount", "type": "i128" }, { "name": "available_at", "type": "u64" }] },
    { "schema_version": "1.0.0", "contract": "fee_collector", "event_name": "FeeRateUpdated", "topics_format": ["symbol:event_name"], "body_fields": [{ "name": "old_rate", "type": "u32" }, { "name": "new_rate", "type": "u32" }, { "name": "updated_by", "type": "Address" }] },
    { "schema_version": "1.0.0", "contract": "fee_collector", "event_name": "TreasuryWithdrawal", "topics_format": ["symbol:event_name"], "body_fields": [{ "name": "recipient", "type": "Address" }, { "name": "token", "type": "Address" }, { "name": "amount", "type": "i128" }, { "name": "remaining_balance", "type": "i128" }] },
    { "schema_version": "1.0.0", "contract": "fee_collector", "event_name": "FeesClaimed", "topics_format": ["symbol:event_name"], "body_fields": [{ "name": "provider", "type": "Address" }, { "name": "token", "type": "Address" }, { "name": "amount", "type": "i128" }] }
  ]
}
